[
    {
        "title": "Chicken Alfredo",
        "description": "A creamy pasta dish with chicken",
        "imageUrl": "https://thecozycook.com/wp-content/uploads/2022/08/Chicken-Alfredo-Pasta-1-1.jpg",
        "link": "/",
        "time_to_cook": "30 minutes",
        "good_in_weather": "cloudy",
        "difficulty": "Medium"
    },
    {
        "title": "Spaghetti and Meatballs",
        "description": "A classic Italian dish",
        "imageUrl": "https://static01.nyt.com/images/2017/04/05/dining/05COOKING-NIGMEATBALLS2/05COOKING-NIGMEATBALLS2-superJumbo.jpg",
        "link": "/",
        "time_to_cook": "30 minutes",
        "good_in_weather": "sunny",
        "difficulty": "Medium"
    },
    {
        "title": "Grilled Cheese",
        "description": "A classic American sandwich",
        "imageUrl": "https://cdn.loveandlemons.com/wp-content/uploads/2023/01/grilled-cheese.jpg",
        "link": "/",
        "time_to_cook": "30 minutes",
        "good_in_weather": "snowy",
        "difficulty": "Hard"
    }
]